timetagger_cli/__init__.py
timetagger_cli/__main__.py
timetagger_cli/config.py
timetagger_cli/core.py
timetagger_cli/utils.py
timetagger_cli-25.5.1.dist-info/LICENSE
timetagger_cli-25.5.1.dist-info/METADATA
timetagger_cli-25.5.1.dist-info/WHEEL
timetagger_cli-25.5.1.dist-info/entry_points.txt
timetagger_cli-25.5.1.dist-info/top_level.txt
timetagger_cli-25.5.1.dist-info/zip-safe
timetagger_cli-25.5.1.dist-info/RECORD
